README.md
setup.py
armrest/__init__.py
armrest/version.py
armrest.egg-info/PKG-INFO
armrest.egg-info/SOURCES.txt
armrest.egg-info/dependency_links.txt
armrest.egg-info/requires.txt
armrest.egg-info/top_level.txt